odoo8_addon_account_bank_statement_import_save_file-8.0.1.0.1.99.dev13-py2.7-nspkg.pth
odoo8_addon_account_bank_statement_import_save_file-8.0.1.0.1.99.dev13.dist-info/METADATA
odoo8_addon_account_bank_statement_import_save_file-8.0.1.0.1.99.dev13.dist-info/RECORD
odoo8_addon_account_bank_statement_import_save_file-8.0.1.0.1.99.dev13.dist-info/WHEEL
odoo8_addon_account_bank_statement_import_save_file-8.0.1.0.1.99.dev13.dist-info/namespace_packages.txt
odoo8_addon_account_bank_statement_import_save_file-8.0.1.0.1.99.dev13.dist-info/top_level.txt
odoo_addons/account_bank_statement_import_save_file/README.rst
odoo_addons/account_bank_statement_import_save_file/__init__.py
odoo_addons/account_bank_statement_import_save_file/__openerp__.py
odoo_addons/account_bank_statement_import_save_file/hooks.py
odoo_addons/account_bank_statement_import_save_file/i18n/account_bank_statement_import_save_file.pot
odoo_addons/account_bank_statement_import_save_file/i18n/de.po
odoo_addons/account_bank_statement_import_save_file/i18n/es.po
odoo_addons/account_bank_statement_import_save_file/i18n/fi.po
odoo_addons/account_bank_statement_import_save_file/i18n/fr.po
odoo_addons/account_bank_statement_import_save_file/i18n/it.po
odoo_addons/account_bank_statement_import_save_file/i18n/lt.po
odoo_addons/account_bank_statement_import_save_file/i18n/lt_LT.po
odoo_addons/account_bank_statement_import_save_file/i18n/nl.po
odoo_addons/account_bank_statement_import_save_file/i18n/pt_BR.po
odoo_addons/account_bank_statement_import_save_file/i18n/pt_PT.po
odoo_addons/account_bank_statement_import_save_file/i18n/sl.po
odoo_addons/account_bank_statement_import_save_file/models/__init__.py
odoo_addons/account_bank_statement_import_save_file/models/account_bank_statement.py
odoo_addons/account_bank_statement_import_save_file/models/account_bank_statement_import.py
odoo_addons/account_bank_statement_import_save_file/static/description/icon.png
odoo_addons/account_bank_statement_import_save_file/tests/__init__.py
odoo_addons/account_bank_statement_import_save_file/tests/test_save_file.py
odoo_addons/account_bank_statement_import_save_file/views/account_bank_statement.xml
