Metadata-Version: 2.1
Name: odoo8-addon-account-bank-statement-import-save-file
Version: 8.0.1.0.1.99.dev13
Summary: Keep imported bank statements as raw data
Home-page: UNKNOWN
Author: Odoo Community Association (OCA), Therp BV
Author-email: support@odoo-community.org
License: AGPL-3
Platform: UNKNOWN
Classifier: Programming Language :: Python
Classifier: Framework :: Odoo
Classifier: License :: OSI Approved :: GNU Affero General Public License v3
Requires-Python: ~=2.7
Requires-Dist: odoo8-addon-account-bank-statement-import
Requires-Dist: odoo (<9.0a,>=8.0a)
